{"version":1,"resource":"file:///src/helloworld/go.mod","entries":[{"id":"sliC.mod","timestamp":1688874650122},{"id":"MAEh.mod","timestamp":1688874947425},{"id":"ZiIQ.mod","source":"Workspace Edit","timestamp":1688875003006},{"id":"fYLi.mod","timestamp":1696728563840},{"id":"5lrl.mod","source":"undoRedo.source","timestamp":1696728568914},{"id":"xtiR.mod","timestamp":1696728662633},{"id":"Q8bw.mod","timestamp":1696728749292},{"id":"3nPz.mod","timestamp":1696728809076},{"id":"mCHV.mod","timestamp":1696728937117},{"id":"TOqz.mod","timestamp":1696728956125},{"id":"pe6a.mod","timestamp":1696728980504},{"id":"Lp3z.mod","timestamp":1696729009044}]}